{
  "filename": "C:\\Users\\Li-Wen Yip\\Documents\\GitHub\\barbershop-scoresheet-scraper\\BABS RTF\\Results-2013-2014-QS-Streamed-Detail.txt",
  "assoc": "BABS",
  "contest": "QUARTET SEMI-FINAL",
  "location": "HARROGATE",
  "year": "2013/2014",
  "type": "q",
  "date": "23/05/2014",
  "judges": [
    {
      "cat": "m",
      "name": "Rod Butcher"
    },
    {
      "cat": "m",
      "name": "Bob Croft"
    },
    {
      "cat": "m",
      "name": "John Palmer"
    },
    {
      "cat": "p",
      "name": "Bob Walker"
    },
    {
      "cat": "p",
      "name": "Nickie James"
    },
    {
      "cat": "p",
      "name": "Pat Deeble"
    },
    {
      "cat": "s",
      "name": "Mark Grindall"
    },
    {
      "cat": "s",
      "name": "David King"
    },
    {
      "cat": "s",
      "name": "Mike Taylor"
    },
    {
      "cat": "a",
      "name": "Alastair Taylor-Payne"
    },
    {
      "cat": "a",
      "name": "Dick Knight"
    },
    {
      "cat": "a",
      "name": "Peter Hughes"
    },
    {
      "cat": "a",
      "name": "Phil Mobsby"
    }
  ],
  "contestants": [
    {
      "rank": 1,
      "name": "RECKLESS",
      "members": [
        {
          "part": "tenor",
          "name": "Andy Foster"
        },
        {
          "part": "lead",
          "name": "Duncan Whinyates"
        },
        {
          "part": "bari",
          "name": "Dale Kynaston"
        },
        {
          "part": "bass",
          "name": "Andy Funnell"
        }
      ],
      "songs": [
        {
          "n": 1,
          "name": "Don't Be A Baby, Baby",
          "m": 238,
          "p": 234,
          "s": 232,
          "tot_score": 704,
          "pc_score": 78.2,
          "m_pc": 79.3,
          "p_pc": 78.0,
          "s_pc": 77.3
        },
        {
          "n": 1,
          "name": "Stormy Weather",
          "m": 244,
          "p": 242,
          "s": 235,
          "tot_score": 721,
          "pc_score": 80.1,
          "m_pc": 81.3,
          "p_pc": 80.7,
          "s_pc": 78.3
        }
      ],
      "n": 2,
      "m": 482,
      "m_pc": 80.3,
      "p": 476,
      "p_pc": 79.3,
      "s": 467,
      "s_pc": 77.8,
      "tot_score": 1425,
      "pc_score": 79.2
    },
    {
      "rank": 2,
      "name": "The Hanfris Quartet",
      "members": [
        {
          "part": "tenor",
          "name": "Jordi Forcadell"
        },
        {
          "part": "lead",
          "name": "Gener Salicr\u00fa"
        },
        {
          "part": "bari",
          "name": "Juan Bertrand"
        },
        {
          "part": "bass",
          "name": "Adri\u00e0 Sivilla"
        }
      ],
      "songs": [
        {
          "n": 1,
          "name": "I Can't Give You Anything But Love",
          "m": 242,
          "p": 229,
          "s": 237,
          "tot_score": 708,
          "pc_score": 78.7,
          "m_pc": 80.7,
          "p_pc": 76.3,
          "s_pc": 79.0
        },
        {
          "n": 1,
          "name": "Make 'Em Laugh",
          "m": 247,
          "p": 231,
          "s": 234,
          "tot_score": 712,
          "pc_score": 79.1,
          "m_pc": 82.3,
          "p_pc": 77.0,
          "s_pc": 78.0
        }
      ],
      "n": 2,
      "m": 489,
      "m_pc": 81.5,
      "p": 460,
      "p_pc": 76.7,
      "s": 471,
      "s_pc": 78.5,
      "tot_score": 1420,
      "pc_score": 78.9
    },
    {
      "rank": 3,
      "name": "Park Street",
      "members": [
        {
          "part": "tenor",
          "name": "Laurence Hasso"
        },
        {
          "part": "lead",
          "name": "Alastair Hay-Plumb"
        },
        {
          "part": "bari",
          "name": "David Foot"
        },
        {
          "part": "bass",
          "name": "Simon Arnott"
        }
      ],
      "songs": [
        {
          "n": 1,
          "name": "Oh, Look At Me Now",
          "m": 239,
          "p": 233,
          "s": 230,
          "tot_score": 702,
          "pc_score": 78.0,
          "m_pc": 79.7,
          "p_pc": 77.7,
          "s_pc": 76.7
        },
        {
          "n": 1,
          "name": "Just A Cottage Small",
          "m": 236,
          "p": 234,
          "s": 231,
          "tot_score": 701,
          "pc_score": 77.9,
          "m_pc": 78.7,
          "p_pc": 78.0,
          "s_pc": 77.0
        }
      ],
      "n": 2,
      "m": 475,
      "m_pc": 79.2,
      "p": 467,
      "p_pc": 77.8,
      "s": 461,
      "s_pc": 76.8,
      "tot_score": 1403,
      "pc_score": 77.9
    },
    {
      "rank": 3,
      "name": "Portobello Road",
      "members": [
        {
          "part": "tenor",
          "name": "Ian James"
        },
        {
          "part": "lead",
          "name": "Brian Schofield"
        },
        {
          "part": "bari",
          "name": "Steve Emery"
        },
        {
          "part": "bass",
          "name": "Stuart Owen"
        }
      ],
      "songs": [
        {
          "n": 1,
          "name": "Wouldn't It Be Loverly",
          "m": 235,
          "p": 233,
          "s": 235,
          "tot_score": 703,
          "pc_score": 78.1,
          "m_pc": 78.3,
          "p_pc": 77.7,
          "s_pc": 78.3
        },
        {
          "n": 1,
          "name": "There, I've Said It Again",
          "m": 233,
          "p": 233,
          "s": 234,
          "tot_score": 700,
          "pc_score": 77.8,
          "m_pc": 77.7,
          "p_pc": 77.7,
          "s_pc": 78.0
        }
      ],
      "n": 2,
      "m": 468,
      "m_pc": 78.0,
      "p": 466,
      "p_pc": 77.7,
      "s": 469,
      "s_pc": 78.2,
      "tot_score": 1403,
      "pc_score": 77.9
    },
    {
      "rank": 5,
      "name": "The Emerald Guard",
      "members": [
        {
          "part": "tenor",
          "name": "Antoine Kaiserman"
        },
        {
          "part": "lead",
          "name": "Tim Briggs"
        },
        {
          "part": "bari",
          "name": "Andy Allen"
        },
        {
          "part": "bass",
          "name": "Duncan Blackeby"
        }
      ],
      "songs": [
        {
          "n": 1,
          "name": "Their Hearts Were Full Of Spring",
          "m": 241,
          "p": 227,
          "s": 227,
          "tot_score": 695,
          "pc_score": 77.2,
          "m_pc": 80.3,
          "p_pc": 75.7,
          "s_pc": 75.7
        },
        {
          "n": 1,
          "name": "Mr. Success",
          "m": 229,
          "p": 230,
          "s": 229,
          "tot_score": 688,
          "pc_score": 76.4,
          "m_pc": 76.3,
          "p_pc": 76.7,
          "s_pc": 76.3
        }
      ],
      "n": 2,
      "m": 470,
      "m_pc": 78.3,
      "p": 457,
      "p_pc": 76.2,
      "s": 456,
      "s_pc": 76.0,
      "tot_score": 1383,
      "pc_score": 76.8
    },
    {
      "rank": 6,
      "name": "HomeSpun",
      "members": [
        {
          "part": "tenor",
          "name": "James Williams"
        },
        {
          "part": "lead",
          "name": "Eddie Williams"
        },
        {
          "part": "bari",
          "name": "Nick Williams"
        },
        {
          "part": "bass",
          "name": "Nigel Williams"
        }
      ],
      "songs": [
        {
          "n": 1,
          "name": "Honey Medley",
          "m": 225,
          "p": 223,
          "s": 222,
          "tot_score": 670,
          "pc_score": 74.4,
          "m_pc": 75.0,
          "p_pc": 74.3,
          "s_pc": 74.0
        },
        {
          "n": 1,
          "name": "Where The Southern Roses Grow",
          "m": 221,
          "p": 226,
          "s": 215,
          "tot_score": 662,
          "pc_score": 73.6,
          "m_pc": 73.7,
          "p_pc": 75.3,
          "s_pc": 71.7
        }
      ],
      "n": 2,
      "m": 446,
      "m_pc": 74.3,
      "p": 449,
      "p_pc": 74.8,
      "s": 437,
      "s_pc": 72.8,
      "tot_score": 1332,
      "pc_score": 74.0
    },
    {
      "rank": 7,
      "name": "QuarteTones",
      "members": [
        {
          "part": "tenor",
          "name": "Graham Harper"
        },
        {
          "part": "lead",
          "name": "Richard Gardner"
        },
        {
          "part": "bari",
          "name": "Alex du Bruin"
        },
        {
          "part": "bass",
          "name": "Iain Hallam"
        }
      ],
      "songs": [
        {
          "n": 1,
          "name": "The Way You Look Tonight",
          "m": 213,
          "p": 218,
          "s": 213,
          "tot_score": 644,
          "pc_score": 71.6,
          "m_pc": 71.0,
          "p_pc": 72.7,
          "s_pc": 71.0
        },
        {
          "n": 1,
          "name": "All Aboard For Dixie Land",
          "m": 228,
          "p": 224,
          "s": 217,
          "tot_score": 669,
          "pc_score": 74.3,
          "m_pc": 76.0,
          "p_pc": 74.7,
          "s_pc": 72.3
        }
      ],
      "n": 2,
      "m": 441,
      "m_pc": 73.5,
      "p": 442,
      "p_pc": 73.7,
      "s": 430,
      "s_pc": 71.7,
      "tot_score": 1313,
      "pc_score": 72.9
    },
    {
      "rank": 8,
      "name": "eXceL",
      "members": [
        {
          "part": "tenor",
          "name": "Simon Hunt"
        },
        {
          "part": "lead",
          "name": "Andy Salter"
        },
        {
          "part": "bari",
          "name": "Dave Whittle"
        },
        {
          "part": "bass",
          "name": "Jon Dawson"
        }
      ],
      "songs": [
        {
          "n": 1,
          "name": "Walkin' My Baby Back Home",
          "m": 216,
          "p": 215,
          "s": 215,
          "tot_score": 646,
          "pc_score": 71.8,
          "m_pc": 72.0,
          "p_pc": 71.7,
          "s_pc": 71.7
        },
        {
          "n": 1,
          "name": "All The Way",
          "m": 224,
          "p": 220,
          "s": 217,
          "tot_score": 661,
          "pc_score": 73.4,
          "m_pc": 74.7,
          "p_pc": 73.3,
          "s_pc": 72.3
        }
      ],
      "n": 2,
      "m": 440,
      "m_pc": 73.3,
      "p": 435,
      "p_pc": 72.5,
      "s": 432,
      "s_pc": 72.0,
      "tot_score": 1307,
      "pc_score": 72.6
    },
    {
      "rank": 9,
      "name": "Tagline",
      "members": [
        {
          "part": "tenor",
          "name": "Ben Ferguson"
        },
        {
          "part": "lead",
          "name": "James Gower-Smith"
        },
        {
          "part": "bari",
          "name": "Chris Langworthy"
        },
        {
          "part": "bass",
          "name": "Rob Foot"
        }
      ],
      "songs": [
        {
          "n": 1,
          "name": "My Romance",
          "m": 228,
          "p": 213,
          "s": 221,
          "tot_score": 662,
          "pc_score": 73.6,
          "m_pc": 76.0,
          "p_pc": 71.0,
          "s_pc": 73.7
        },
        {
          "n": 1,
          "name": "Everybody Needs A Best Friend",
          "m": 216,
          "p": 212,
          "s": 215,
          "tot_score": 643,
          "pc_score": 71.4,
          "m_pc": 72.0,
          "p_pc": 70.7,
          "s_pc": 71.7
        }
      ],
      "n": 2,
      "m": 444,
      "m_pc": 74.0,
      "p": 425,
      "p_pc": 70.8,
      "s": 436,
      "s_pc": 72.7,
      "tot_score": 1305,
      "pc_score": 72.5
    },
    {
      "rank": 10,
      "name": "The Simpletones",
      "members": [
        {
          "part": "tenor",
          "name": "Nick Pawley"
        },
        {
          "part": "lead",
          "name": "Simon Lubkowski"
        },
        {
          "part": "bari",
          "name": "Nik Robinson"
        },
        {
          "part": "bass",
          "name": "Ian White"
        }
      ],
      "songs": [
        {
          "n": 1,
          "name": "I Won't Send Roses",
          "m": 207,
          "p": 209,
          "s": 196,
          "tot_score": 612,
          "pc_score": 68.0,
          "m_pc": 69.0,
          "p_pc": 69.7,
          "s_pc": 65.3
        },
        {
          "n": 1,
          "name": "Oh! Look At Me Now",
          "m": 208,
          "p": 206,
          "s": 196,
          "tot_score": 610,
          "pc_score": 67.8,
          "m_pc": 69.3,
          "p_pc": 68.7,
          "s_pc": 65.3
        }
      ],
      "n": 2,
      "m": 415,
      "m_pc": 69.2,
      "p": 415,
      "p_pc": 69.2,
      "s": 392,
      "s_pc": 65.3,
      "tot_score": 1222,
      "pc_score": 67.9
    },
    {
      "rank": 11,
      "name": "Soundcheck",
      "members": [
        {
          "part": "tenor",
          "name": "Alan Wright"
        },
        {
          "part": "lead",
          "name": "Paul Gidney"
        },
        {
          "part": "bari",
          "name": "Jack Haslam"
        },
        {
          "part": "bass",
          "name": "John Clarke"
        }
      ],
      "songs": [
        {
          "n": 1,
          "name": "The Way You Look Tonight",
          "m": 202,
          "p": 204,
          "s": 205,
          "tot_score": 611,
          "pc_score": 67.9,
          "m_pc": 67.3,
          "p_pc": 68.0,
          "s_pc": 68.3
        },
        {
          "n": 1,
          "name": "It Happened In Monterey",
          "m": 198,
          "p": 200,
          "s": 195,
          "tot_score": 593,
          "pc_score": 65.9,
          "m_pc": 66.0,
          "p_pc": 66.7,
          "s_pc": 65.0
        }
      ],
      "n": 2,
      "m": 400,
      "m_pc": 66.7,
      "p": 404,
      "p_pc": 67.3,
      "s": 400,
      "s_pc": 66.7,
      "tot_score": 1204,
      "pc_score": 66.9
    },
    {
      "rank": 12,
      "name": "QM",
      "members": [
        {
          "part": "tenor",
          "name": "Paul Jeffrey"
        },
        {
          "part": "lead",
          "name": "Trevor Dawson"
        },
        {
          "part": "bari",
          "name": "Adrian Armstrong"
        },
        {
          "part": "bass",
          "name": "Steve Cox"
        }
      ],
      "songs": [
        {
          "n": 1,
          "name": "It's Only A Paper Moon",
          "m": 204,
          "p": 203,
          "s": 194,
          "tot_score": 601,
          "pc_score": 66.8,
          "m_pc": 68.0,
          "p_pc": 67.7,
          "s_pc": 64.7
        },
        {
          "n": 1,
          "name": "The Little Boy",
          "m": 196,
          "p": 202,
          "s": 192,
          "tot_score": 590,
          "pc_score": 65.6,
          "m_pc": 65.3,
          "p_pc": 67.3,
          "s_pc": 64.0
        }
      ],
      "n": 2,
      "m": 400,
      "m_pc": 66.7,
      "p": 405,
      "p_pc": 67.5,
      "s": 386,
      "s_pc": 64.3,
      "tot_score": 1191,
      "pc_score": 66.2
    },
    {
      "rank": 13,
      "name": "Price Tag",
      "members": [
        {
          "part": "tenor",
          "name": "Steve Cox"
        },
        {
          "part": "lead",
          "name": "Andy McPhee"
        },
        {
          "part": "bari",
          "name": "Dan Jones"
        },
        {
          "part": "bass",
          "name": "Graeme Crawford"
        }
      ],
      "songs": [
        {
          "n": 1,
          "name": "That's Life",
          "m": 202,
          "p": 196,
          "s": 189,
          "tot_score": 587,
          "pc_score": 65.2,
          "m_pc": 67.3,
          "p_pc": 65.3,
          "s_pc": 63.0
        },
        {
          "n": 1,
          "name": "Once Upon A Time",
          "m": 205,
          "p": 196,
          "s": 184,
          "tot_score": 585,
          "pc_score": 65.0,
          "m_pc": 68.3,
          "p_pc": 65.3,
          "s_pc": 61.3
        }
      ],
      "n": 2,
      "m": 407,
      "m_pc": 67.8,
      "p": 392,
      "p_pc": 65.3,
      "s": 373,
      "s_pc": 62.2,
      "tot_score": 1172,
      "pc_score": 65.1
    },
    {
      "rank": 14,
      "name": "Figaro",
      "members": [
        {
          "part": "tenor",
          "name": "Aidan Brand"
        },
        {
          "part": "lead",
          "name": "Rob Langley Jones"
        },
        {
          "part": "bari",
          "name": "Andy Rzysko"
        },
        {
          "part": "bass",
          "name": "Richard Leatham"
        }
      ],
      "songs": [
        {
          "n": 1,
          "name": "Old St. Louis",
          "m": 190,
          "p": 200,
          "s": 191,
          "tot_score": 581,
          "pc_score": 64.6,
          "m_pc": 63.3,
          "p_pc": 66.7,
          "s_pc": 63.7
        },
        {
          "n": 1,
          "name": "Beautiful Dreamer",
          "m": 194,
          "p": 204,
          "s": 189,
          "tot_score": 587,
          "pc_score": 65.2,
          "m_pc": 64.7,
          "p_pc": 68.0,
          "s_pc": 63.0
        }
      ],
      "n": 2,
      "m": 384,
      "m_pc": 64.0,
      "p": 404,
      "p_pc": 67.3,
      "s": 380,
      "s_pc": 63.3,
      "tot_score": 1168,
      "pc_score": 64.9
    },
    {
      "rank": 15,
      "name": "The Grand Dads",
      "members": [
        {
          "part": "tenor",
          "name": "Mick Barnacle"
        },
        {
          "part": "lead",
          "name": "Rob Parnham"
        },
        {
          "part": "bari",
          "name": "Dave Hughes"
        },
        {
          "part": "bass",
          "name": "Rob Taylor"
        }
      ],
      "songs": [
        {
          "n": 1,
          "name": "When The Gold Turns To Grey",
          "m": 199,
          "p": 204,
          "s": 187,
          "tot_score": 590,
          "pc_score": 65.6,
          "m_pc": 66.3,
          "p_pc": 68.0,
          "s_pc": 62.3
        },
        {
          "n": 1,
          "name": "Bring Back Those Good Old Days",
          "m": 195,
          "p": 197,
          "s": 185,
          "tot_score": 577,
          "pc_score": 64.1,
          "m_pc": 65.0,
          "p_pc": 65.7,
          "s_pc": 61.7
        }
      ],
      "n": 2,
      "m": 394,
      "m_pc": 65.7,
      "p": 401,
      "p_pc": 66.8,
      "s": 372,
      "s_pc": 62.0,
      "tot_score": 1167,
      "pc_score": 64.8
    },
    {
      "rank": 16,
      "name": "The Tagpipes",
      "members": [
        {
          "part": "tenor",
          "name": "Callum Rickard"
        },
        {
          "part": "lead",
          "name": "Shaun McCormack"
        },
        {
          "part": "bari",
          "name": "David Sangster"
        },
        {
          "part": "bass",
          "name": "Nick Drew"
        }
      ],
      "songs": [
        {
          "n": 1,
          "name": "Come Fly With Me",
          "m": 195,
          "p": 191,
          "s": 195,
          "tot_score": 581,
          "pc_score": 64.6,
          "m_pc": 65.0,
          "p_pc": 63.7,
          "s_pc": 65.0
        },
        {
          "n": 1,
          "name": "Love Me And The World Is Mine",
          "m": 201,
          "p": 188,
          "s": 192,
          "tot_score": 581,
          "pc_score": 64.6,
          "m_pc": 67.0,
          "p_pc": 62.7,
          "s_pc": 64.0
        }
      ],
      "n": 2,
      "m": 396,
      "m_pc": 66.0,
      "p": 379,
      "p_pc": 63.2,
      "s": 387,
      "s_pc": 64.5,
      "tot_score": 1162,
      "pc_score": 64.6
    },
    {
      "rank": 17,
      "name": "The Moondogs",
      "members": [
        {
          "part": "tenor",
          "name": "Vaughan Dooley"
        },
        {
          "part": "lead",
          "name": "Jony Coulter"
        },
        {
          "part": "bari",
          "name": "Dean Whitehouse"
        },
        {
          "part": "bass",
          "name": "Peter Blackeby"
        }
      ],
      "songs": [
        {
          "n": 1,
          "name": "The Masquerade Is Over",
          "m": 194,
          "p": 196,
          "s": 187,
          "tot_score": 577,
          "pc_score": 64.1,
          "m_pc": 64.7,
          "p_pc": 65.3,
          "s_pc": 62.3
        },
        {
          "n": 1,
          "name": "Undecided Medley",
          "m": 197,
          "p": 195,
          "s": 187,
          "tot_score": 579,
          "pc_score": 64.3,
          "m_pc": 65.7,
          "p_pc": 65.0,
          "s_pc": 62.3
        }
      ],
      "n": 2,
      "m": 391,
      "m_pc": 65.2,
      "p": 391,
      "p_pc": 65.2,
      "s": 374,
      "s_pc": 62.3,
      "tot_score": 1156,
      "pc_score": 64.2
    },
    {
      "rank": 18,
      "name": "Graffiti",
      "members": [
        {
          "part": "tenor",
          "name": "Nick Howell"
        },
        {
          "part": "lead",
          "name": "Terry Mansfield"
        },
        {
          "part": "bari",
          "name": "Gary Roussak"
        },
        {
          "part": "bass",
          "name": "Peter Williams"
        }
      ],
      "songs": [
        {
          "n": 1,
          "name": "You're Nobody 'Til Somebody Loves You",
          "m": 190,
          "p": 198,
          "s": 182,
          "tot_score": 570,
          "pc_score": 63.3,
          "m_pc": 63.3,
          "p_pc": 66.0,
          "s_pc": 60.7
        },
        {
          "n": 1,
          "name": "Once Upon A Time",
          "m": 183,
          "p": 195,
          "s": 177,
          "tot_score": 555,
          "pc_score": 61.7,
          "m_pc": 61.0,
          "p_pc": 65.0,
          "s_pc": 59.0
        }
      ],
      "n": 2,
      "m": 373,
      "m_pc": 62.2,
      "p": 393,
      "p_pc": 65.5,
      "s": 359,
      "s_pc": 59.8,
      "tot_score": 1125,
      "pc_score": 62.5
    },
    {
      "rank": 19,
      "name": "Sparks",
      "members": [
        {
          "part": "tenor",
          "name": "Hayden Cole"
        },
        {
          "part": "lead",
          "name": "John Ward"
        },
        {
          "part": "bari",
          "name": "Ian Saxby"
        },
        {
          "part": "bass",
          "name": "Steven Neck"
        }
      ],
      "songs": [
        {
          "n": 1,
          "name": "They Say It's Wonderful",
          "m": 190,
          "p": 196,
          "s": 183,
          "tot_score": 569,
          "pc_score": 63.2,
          "m_pc": 63.3,
          "p_pc": 65.3,
          "s_pc": 61.0
        },
        {
          "n": 1,
          "name": "Almost Like Being In Love",
          "m": 179,
          "p": 190,
          "s": 180,
          "tot_score": 549,
          "pc_score": 61.0,
          "m_pc": 59.7,
          "p_pc": 63.3,
          "s_pc": 60.0
        }
      ],
      "n": 2,
      "m": 369,
      "m_pc": 61.5,
      "p": 386,
      "p_pc": 64.3,
      "s": 363,
      "s_pc": 60.5,
      "tot_score": 1118,
      "pc_score": 62.1
    }
  ]
}